EntityRelation/EntityRelation.py
EntityRelation/__init__.py
EntityRelation/core/__init__.py
EntityRelation/core/core.py
EntityRelation/core/extract_by_dsnf.py
EntityRelation/core/extractor.py
EntityRelation/resource/user_dict.txt
EntityRelation/utils/__init__.py
EntityRelation/utils/utils.py
test/__init__.py
test/test.py
EntityRelation-1.0.3.dist-info/LICENSE
EntityRelation-1.0.3.dist-info/METADATA
EntityRelation-1.0.3.dist-info/WHEEL
EntityRelation-1.0.3.dist-info/top_level.txt
EntityRelation-1.0.3.dist-info/RECORD
